ukrdict/__init__.py
ukrdict/__main__.py
ukrdict/ukrdict.py
ukrdict-0.1.6.dist-info/entry_points.txt
ukrdict-0.1.6.dist-info/LICENSE
ukrdict-0.1.6.dist-info/WHEEL
ukrdict-0.1.6.dist-info/METADATA
ukrdict-0.1.6.dist-info/RECORD
